fips_agents_cli/__init__.py
fips_agents_cli/__main__.py
fips_agents_cli/cli.py
fips_agents_cli/version.py
fips_agents_cli/commands/__init__.py
fips_agents_cli/commands/create.py
fips_agents_cli/commands/generate.py
fips_agents_cli/commands/model_car.py
fips_agents_cli/commands/patch.py
fips_agents_cli/tools/__init__.py
fips_agents_cli/tools/filesystem.py
fips_agents_cli/tools/generators.py
fips_agents_cli/tools/git.py
fips_agents_cli/tools/github.py
fips_agents_cli/tools/patching.py
fips_agents_cli/tools/project.py
fips_agents_cli/tools/validation.py
fips_agents_cli-0.2.0.dist-info/METADATA
fips_agents_cli-0.2.0.dist-info/WHEEL
fips_agents_cli-0.2.0.dist-info/entry_points.txt
fips_agents_cli-0.2.0.dist-info/licenses/LICENSE
fips_agents_cli-0.2.0.dist-info/RECORD
