Metadata-Version: 2.4
Name: fips-agents-cli
Version: 0.2.0
Summary: CLI tool for creating and managing FIPS-compliant AI agent projects
Project-URL: Homepage, https://github.com/rdwj/fips-agents-cli
Project-URL: Repository, https://github.com/rdwj/fips-agents-cli
Project-URL: Issues, https://github.com/rdwj/fips-agents-cli/issues
Author-email: Wes Jackson <wjackson@redhat.com>
License: MIT
License-File: LICENSE
Keywords: agents,ai,cli,code-generator,fips,mcp,scaffolding
Classifier: Development Status :: 3 - Alpha
Classifier: Intended Audience :: Developers
Classifier: License :: OSI Approved :: MIT License
Classifier: Programming Language :: Python :: 3
Classifier: Programming Language :: Python :: 3.10
Classifier: Programming Language :: Python :: 3.11
Classifier: Programming Language :: Python :: 3.12
Classifier: Topic :: Software Development :: Code Generators
Classifier: Topic :: Software Development :: Libraries :: Application Frameworks
Requires-Python: >=3.10
Requires-Dist: click>=8.1.0
Requires-Dist: gitpython>=3.1.0
Requires-Dist: jinja2>=3.1.2
Requires-Dist: rich>=13.0.0
Requires-Dist: tomlkit>=0.12.0
Provides-Extra: dev
Requires-Dist: black>=23.0.0; extra == 'dev'
Requires-Dist: pytest-cov>=4.1.0; extra == 'dev'
Requires-Dist: pytest>=7.4.0; extra == 'dev'
Requires-Dist: ruff>=0.1.0; extra == 'dev'
